README.md
setup.py
yulksync/__init__.py
yulksync/__main__.py
yulksync.egg-info/PKG-INFO
yulksync.egg-info/SOURCES.txt
yulksync.egg-info/dependency_links.txt
yulksync.egg-info/requires.txt
yulksync.egg-info/top_level.txt