Metadata-Version: 2.1
Name: yulksync
Version: 0.0.2
Summary: yulksync
Home-page: https://github.com/
Author: yulksync
Author-email: 1918118941@qq.com
Classifier: Programming Language :: Python :: 3
Classifier: License :: OSI Approved :: MIT License
Classifier: Operating System :: OS Independent
Requires-Dist: requests
Requires-Dist: fire>=0.7.1
Requires-Dist: wget>=3.2
